ikengine/__init__.py
3dof_hexapod_ik_generator-1.0.0.dist-info/LICENSE
3dof_hexapod_ik_generator-1.0.0.dist-info/METADATA
3dof_hexapod_ik_generator-1.0.0.dist-info/WHEEL
3dof_hexapod_ik_generator-1.0.0.dist-info/top_level.txt
3dof_hexapod_ik_generator-1.0.0.dist-info/RECORD
