Metadata-Version: 2.1
Name: 3dof-hexapod-ik-generator
Version: 1.0.0
Summary: This is a module which calculates IK servo angles for leaning and shifting a 3dof hexapod's body.
Home-page: https://github.com/macaquedev
Author: Alex Pylypenko (macaquedev)
Author-email: macaquedev@gmail.com
License: MIT
Platform: UNKNOWN
Classifier: License :: OSI Approved :: MIT License
Classifier: Programming Language :: Python :: 3
Classifier: Programming Language :: Python :: 3.7
